cvx/cook.py
cvx/cooker/__init__.py
cvx/cooker/parse.py
cvx/templates/readme/README.md
cvxcooker-0.0.6.dist-info/METADATA
cvxcooker-0.0.6.dist-info/WHEEL
cvxcooker-0.0.6.dist-info/entry_points.txt
cvxcooker-0.0.6.dist-info/licenses/LICENSE
cvxcooker-0.0.6.dist-info/RECORD
