Metadata-Version: 2.4
Name: cvxcooker
Version: 0.0.6
Summary: ...
Project-URL: repository, https://github.com/cvxgrp/boilerplate
Project-URL: homepage, https://www.cvxgrp.com/boilerplate
Author-email: Thomas Schmelzer <thomas.schmelzer@gmail.com>
License-File: LICENSE
Requires-Python: >=3.10
Requires-Dist: fire>=0.7.0
Requires-Dist: jinja2>=3.1.5
Requires-Dist: loguru>=0.7.3
Requires-Dist: toml>=0.10.2
Provides-Extra: dev
Requires-Dist: pre-commit>=4.0.1; extra == 'dev'
Requires-Dist: pytest-cov>=6.0.0; extra == 'dev'
Requires-Dist: pytest>=8.3.3; extra == 'dev'
